{
  "sheetsById": {
    "Animated scene": {
      "staticOverrides": {
        "byObject": {}
      },
      "sequence": {
        "subUnitsPerUnit": 30,
        "length": 10,
        "type": "PositionalSequence",
        "tracksByObject": {
          "Torus Knot": {
            "trackData": {
              "eiVq31EVQ6": {
                "type": "BasicKeyframedTrack",
                "__debugName": "Torus Knot:[\"rotation\",\"x\"]",
                "keyframes": [
                  {
                    "id": "nxZLSj9mRl",
                    "position": 5.167,
                    "connectedRight": true,
                    "handles": [
                      0.5,
                      1,
                      0.5,
                      0
                    ],
                    "type": "bezier",
                    "value": 30
                  },
                  {
                    "id": "8bVVm7SHd4",
                    "position": 5.867,
                    "connectedRight": true,
                    "handles": [
                      0.5,
                      1,
                      0.5,
                      0
                    ],
                    "type": "bezier",
                    "value": 0
                  }
                ]
              },
              "xVDXtCBmw6": {
                "type": "BasicKeyframedTrack",
                "__debugName": "Torus Knot:[\"rotation\",\"y\"]",
                "keyframes": [
                  {
                    "id": "yfZZImD3HB",
                    "position": 5.167,
                    "connectedRight": true,
                    "handles": [
                      0.5,
                      1,
                      0.5,
                      0
                    ],
                    "type": "bezier",
                    "value": 0
                  }
                ]
              },
              "RreRMZKtX3": {
                "type": "BasicKeyframedTrack",
                "__debugName": "Torus Knot:[\"rotation\",\"z\"]",
                "keyframes": [
                  {
                    "id": "ckiM2hZuyl",
                    "position": 5.167,
                    "connectedRight": true,
                    "handles": [
                      0.5,
                      1,
                      0.5,
                      0
                    ],
                    "type": "bezier",
                    "value": 0
                  }
                ]
              }
            },
            "trackIdByPropPath": {
              "[\"rotation\",\"x\"]": "eiVq31EVQ6",
              "[\"rotation\",\"y\"]": "xVDXtCBmw6",
              "[\"rotation\",\"z\"]": "RreRMZKtX3"
            }
          }
        }
      }
    }
  },
  "definitionVersion": "0.4.0",
  "revisionHistory": [
    "Tc9cBeONnxugw2VM",
    "sT2s1l54Y61a1ItN"
  ]
}